concave/__init__.py
concave/exceptions.py
concave/results.py
concave/sandbox.py
concave/namespaces/__init__.py
concave/namespaces/files.py
concave/namespaces/monitor.py
concave/namespaces/network.py
concave_sandbox-0.7.2.dist-info/licenses/LICENSE
concave_sandbox-0.7.2.dist-info/METADATA
concave_sandbox-0.7.2.dist-info/WHEEL
concave_sandbox-0.7.2.dist-info/top_level.txt
concave_sandbox-0.7.2.dist-info/RECORD
