Metadata-Version: 2.4
Name: concave-sandbox
Version: 0.7.2
Summary: Python SDK for Concave - Secure Sandboxes for AI Agents
Author: Concave
Maintainer: Concave
License-Expression: MIT
Project-URL: Homepage, https://concave.ai
Project-URL: Documentation, https://docs.concave.ai
Project-URL: Repository, https://github.com/ConcaveAI/concave-sandbox
Project-URL: Issues, https://github.com/ConcaveAI/concave-sandbox/issues
Keywords: sandbox,code-execution,firecracker,isolation,security,concave
Classifier: Intended Audience :: Developers
Classifier: Topic :: Software Development :: Libraries :: Python Modules
Classifier: Topic :: System :: Emulators
Classifier: Topic :: Security
Requires-Python: >=3.8
License-File: LICENSE
Requires-Dist: httpx>=0.25.0
Dynamic: license-file
